{
    "people": [
        {
            "id": 1,
            "name": "Blondy Emons",
            "contact": "180 717 5291",
            "email": "bemons0@ibm.com",
            "title": "Social Worker"
        },
        {
            "id": 2,
            "name": "Hillary Seignior",
            "contact": "554 121 4225",
            "email": "hseignior1@is.gd",
            "title": "Nuclear Power Engineer"
        },
        {
            "id": 3,
            "name": "Cly Scorton",
            "contact": "774 658 9590",
            "email": "cscorton2@t.co",
            "title": "Database Administrator IV"
        },
        {
            "id": 4,
            "name": "Libbey Rosenblad",
            "contact": "887 189 4313",
            "email": "lrosenblad3@geographic.com",
            "title": "Environmental Specialist"
        },
        {
            "id": 5,
            "name": "Alisha Gibling",
            "contact": "212 254 9846",
            "email": "agibling4@jigsy.com",
            "title": "Research Assistant III"
        },
        {
            "id": 6,
            "name": "Alexina Stittle",
            "contact": "943 809 1785",
            "email": "astittle5@bloglines.com",
            "title": "Computer Systems Analyst I"
        },
        {
            "id": 7,
            "name": "Oralle Goulston",
            "contact": "120 264 4945",
            "email": "ogoulston6@oracle.com",
            "title": "Tax Accountant"
        },
        {
            "id": 8,
            "name": "Kingston McEttigen",
            "contact": "637 490 3704",
            "email": "kmcettigen7@over-blog.com",
            "title": "Computer Systems Analyst I"
        },
        {
            "id": 9,
            "name": "Quent Mulvenna",
            "contact": "867 539 0809",
            "email": "qmulvenna8@indiatimes.com",
            "title": "Statistician I"
        },
        {
            "id": 10,
            "name": "Clare Hast",
            "contact": "447 959 0318",
            "email": "chast9@wp.com",
            "title": "Accounting Assistant IV"
        },
        {
            "id": 11,
            "name": "Dixie Emerine",
            "contact": "904 691 1345",
            "email": "demerinea@de.vu",
            "title": "Desktop Support Technician"
        },
        {
            "id": 12,
            "name": "Doro Burke",
            "contact": "283 880 8904",
            "email": "dburkeb@123-reg.co.uk",
            "title": "Clinical Specialist"
        },
        {
            "id": 13,
            "name": "Ruby Harewood",
            "contact": "680 719 2859",
            "email": "rharewoodc@usatoday.com",
            "title": "Assistant Manager"
        },
        {
            "id": 14,
            "name": "Sasha Stairs",
            "contact": "646 741 0248",
            "email": "sstairsd@joomla.org",
            "title": "Engineer I"
        },
        {
            "id": 15,
            "name": "Catlee Cashmore",
            "contact": "134 791 1691",
            "email": "ccashmoree@wisc.edu",
            "title": "Senior Editor"
        },
        {
            "id": 16,
            "name": "Josias Halfpenny",
            "contact": "180 380 9882",
            "email": "jhalfpennyf@weebly.com",
            "title": "Administrative Assistant III"
        },
        {
            "id": 17,
            "name": "Boothe How to preserve",
            "contact": "966 568 3498",
            "email": "bhowg@independent.co.uk",
            "title": "Software Engineer III"
        },
        {
            "id": 18,
            "name": "Aryn Lorenzin",
            "contact": "462 238 7334",
            "email": "alorenzinh@upenn.edu",
            "title": "Research Assistant III"
        },
        {
            "id": 19,
            "name": "Alaster Feechum",
            "contact": "469 390 9201",
            "email": "afeechumi@weibo.com",
            "title": "Analog Circuit Design manager"
        },
        {
            "id": 20,
            "name": "Michaelina Kettridge",
            "contact": "180 769 3036",
            "email": "mkettridgej@census.gov",
            "title": "Web Designer IV"
        },
        {
            "id": 21,
            "name": "Engelbert Baumber",
            "contact": "571 382 4085",
            "email": "ebaumberk@bravesites.com",
            "title": "Assistant Media Planner"
        },
        {
            "id": 22,
            "name": "Mariann De Cruze",
            "contact": "480 616 2855",
            "email": "mdel@engadget.com",
            "title": "Associate Professor"
        },
        {
            "id": 23,
            "name": "Howard Latta",
            "contact": "395 744 6972",
            "email": "hlattam@parallels.com",
            "title": "Programmer IV"
        },
        {
            "id": 24,
            "name": "Caron Konke",
            "contact": "479 833 1303",
            "email": "ckonken@slashdot.org",
            "title": "Professor"
        },
        {
            "id": 25,
            "name": "Sallee Robus",
            "contact": "676 549 2088",
            "email": "srobuso@columbia.edu",
            "title": "Safety Technician II"
        },
        {
            "id": 26,
            "name": "Bruce Spurnier",
            "contact": "807 624 3761",
            "email": "bspurnierp@un.org",
            "title": "Administrative Assistant IV"
        },
        {
            "id": 27,
            "name": "Cal Kinkead",
            "contact": "580 119 7768",
            "email": "ckinkeadq@printfriendly.com",
            "title": "Help Desk Technician"
        },
        {
            "id": 28,
            "name": "Boote Woolcocks",
            "contact": "526 387 9262",
            "email": "bwoolcocksr@comsenz.com",
            "title": "Chief Design Engineer"
        },
        {
            "id": 29,
            "name": "Libby Malin",
            "contact": "164 550 1122",
            "email": "lmalins@blogger.com",
            "title": "Mechanical Systems Engineer"
        },
        {
            "id": 30,
            "name": "Mickie Petrescu",
            "contact": "540 318 3467",
            "email": "mpetrescut@sbwire.com",
            "title": "General Manager"
        },
        {
            "id": 31,
            "name": "Winona Dodgson",
            "contact": "278 800 9614",
            "email": "wdodgsonu@mac.com",
            "title": "Actuary"
        },
        {
            "id": 32,
            "name": "Charline Divina",
            "contact": "949 925 9126",
            "email": "cdivinav@bing.com",
            "title": "Design Engineer"
        },
        {
            "id": 33,
            "name": "Kristoforo Henniger",
            "contact": "570 360 9936",
            "email": "khennigerw@pagesperso-orange.fr",
            "title": "Account Coordinator"
        },
        {
            "id": 34,
            "name": "Fawn Smouten",
            "contact": "911 919 0757",
            "email": "fsmoutenx@paginegialle.it",
            "title": "Account Representative II"
        },
        {
            "id": 35,
            "name": "Maurise Britt",
            "contact": "805 695 6038",
            "email": "mbritty@1688.com",
            "title": "Executive Secretary"
        },
        {
            "id": 36,
            "name": "Emma Tosspell",
            "contact": "143 969 0718",
            "email": "etosspellz@apple.com",
            "title": "GIS Technical Architect"
        },
        {
            "id": 37,
            "name": "Mylo Melanaphy",
            "contact": "815 544 7862",
            "email": "mmelanaphy10@cornell.edu",
            "title": "Chief Design Engineer"
        },
        {
            "id": 38,
            "name": "Tobias Smedmore",
            "contact": "498 777 9325",
            "email": "tsmedmore11@nytimes.com",
            "title": "Statistician III"
        },
        {
            "id": 39,
            "name": "Darbie Klesel",
            "contact": "607 750 5847",
            "email": "dklesel12@nymag.com",
            "title": "Internal Auditor"
        },
        {
            "id": 40,
            "name": "Allie Rickertsen",
            "contact": "761 856 4689",
            "email": "arickertsen13@e-recht24.de",
            "title": "Staff Accountant IV"
        },
        {
            "id": 41,
            "name": "Fonz Aglione",
            "contact": "941 321 0591",
            "email": "faglione14@fema.gov",
            "title": "VP Quality Control"
        },
        {
            "id": 42,
            "name": "Quent Purry",
            "contact": "458 514 1668",
            "email": "qpurry15@huffingtonpost.com",
            "title": "Quality Engineer"
        },
        {
            "id": 43,
            "name": "Kathrine Rosling",
            "contact": "475 477 6968",
            "email": "krosling16@surveymonkey.com",
            "title": "VP Marketing"
        },
        {
            "id": 44,
            "name": "Alix Larrad",
            "contact": "764 356 8331",
            "email": "alarrad17@discovery.com",
            "title": "Database Administrator II"
        },
        {
            "id": 45,
            "name": "Marcelle Edy",
            "contact": "380 764 1886",
            "email": "medy18@acquirethisname.com",
            "title": "Graphic Designer"
        },
        {
            "id": 46,
            "name": "Mendel Skilbeck",
            "contact": "927 907 2225",
            "email": "mskilbeck19@studiopress.com",
            "title": "Database Administrator II"
        },
        {
            "id": 47,
            "name": "Morgen Stocken",
            "contact": "481 517 2067",
            "email": "mstocken1a@nationalgeographic.com",
            "title": "Nuclear Power Engineer"
        },
        {
            "id": 48,
            "name": "Rhea Blackledge",
            "contact": "206 978 1306",
            "email": "rblackledge1b@fastcompany.com",
            "title": "Analyst Programmer"
        },
        {
            "id": 49,
            "name": "Kissie Sammes",
            "contact": "749 216 9181",
            "email": "ksammes1c@tumblr.com",
            "title": "Budget/Accounting Analyst II"
        },
        {
            "id": 50,
            "name": "Vladimir Meindl",
            "contact": "120 892 8927",
            "email": "vmeindl1d@ezinearticles.com",
            "title": "Professor"
        },
        {
            "id": 51,
            "name": "Carlota Lavington",
            "contact": "346 165 9609",
            "email": "clavington1e@chicagotribune.com",
            "title": "Web Developer II"
        },
        {
            "id": 52,
            "name": "Brietta Rizzolo",
            "contact": "804 665 6480",
            "email": "brizzolo1f@irs.gov",
            "title": "Quality Engineer"
        },
        {
            "id": 53,
            "name": "Neille Billett",
            "contact": "379 940 4898",
            "email": "nbillett1g@admin.ch",
            "title": "Technical Writer"
        },
        {
            "id": 54,
            "name": "Eb Carriage",
            "contact": "199 528 0526",
            "email": "ecarriage1h@cocolog-nifty.com",
            "title": "Human Resources Assistant III"
        },
        {
            "id": 55,
            "name": "Rianon Rushsorth",
            "contact": "174 697 9525",
            "email": "rrushsorth1i@addtoany.com",
            "title": "Help Desk Technician"
        },
        {
            "id": 56,
            "name": "Emelia O' Meara",
            "contact": "543 644 7870",
            "email": "eo1j@tripod.com",
            "title": "Community Outreach Specialist"
        },
        {
            "id": 57,
            "name": "Merwyn Chrisp",
            "contact": "181 147 7196",
            "email": "mchrisp1k@japanpost.jp",
            "title": "Health Coach II"
        },
        {
            "id": 58,
            "name": "Donaugh Frede",
            "contact": "935 314 0994",
            "email": "dfrede1l@oakley.com",
            "title": "Junior Executive"
        },
        {
            "id": 59,
            "name": "Shelly McKevitt",
            "contact": "660 315 6863",
            "email": "smckevitt1m@ft.com",
            "title": "Account Representative IV"
        },
        {
            "id": 60,
            "name": "Berny Saylor",
            "contact": "371 440 8729",
            "email": "bsaylor1n@parallels.com",
            "title": "Compensation Analyst"
        },
        {
            "id": 61,
            "name": "Giustino MacNair",
            "contact": "788 344 4540",
            "email": "gmacnair1o@arstechnica.com",
            "title": "Marketing Manager"
        },
        {
            "id": 62,
            "name": "Salomi Hegdonne",
            "contact": "714 265 2787",
            "email": "shegdonne1p@home.pl",
            "title": "Programmer Analyst II"
        },
        {
            "id": 63,
            "name": "Niels Iredale",
            "contact": "925 908 4537",
            "email": "niredale1q@xrea.com",
            "title": "Clinical Specialist"
        },
        {
            "id": 64,
            "name": "Gretel Curton",
            "contact": "812 873 3672",
            "email": "gcurton1r@soundcloud.com",
            "title": "Database Administrator III"
        },
        {
            "id": 65,
            "name": "Dee MacAllester",
            "contact": "427 518 9412",
            "email": "dmacallester1s@mozilla.org",
            "title": "Business Systems Development Analyst"
        },
        {
            "id": 66,
            "name": "Marmaduke McFadden",
            "contact": "308 537 9963",
            "email": "mmcfadden1t@twitter.com",
            "title": "Social Worker"
        },
        {
            "id": 67,
            "name": "Jeramie Maggiori",
            "contact": "336 198 7066",
            "email": "jmaggiori1u@wisc.edu",
            "title": "Actuary"
        },
        {
            "id": 68,
            "name": "Carey Heiton",
            "contact": "257 877 0287",
            "email": "cheiton1v@creativecommons.org",
            "title": "Assistant Professor"
        },
        {
            "id": 69,
            "name": "Marc McWhin",
            "contact": "809 826 7075",
            "email": "mmcwhin1w@sogou.com",
            "title": "Administrative Officer"
        },
        {
            "id": 70,
            "name": "Luigi Merigon",
            "contact": "440 479 5667",
            "email": "lmerigon1x@tripadvisor.com",
            "title": "Marketing Manager"
        },
        {
            "id": 71,
            "name": "Adriano Babar",
            "contact": "681 312 3540",
            "email": "ababar1y@timesonline.co.uk",
            "title": "VP Marketing"
        },
        {
            "id": 72,
            "name": "Keary Kirsop",
            "contact": "580 900 3218",
            "email": "kkirsop1z@joomla.org",
            "title": "VP Quality Control"
        },
        {
            "id": 73,
            "name": "Cyrillus Shulem",
            "contact": "533 398 8764",
            "email": "cshulem20@cnbc.com",
            "title": "Cost Accountant"
        },
        {
            "id": 74,
            "name": "Ivory Dougary",
            "contact": "405 894 8102",
            "email": "idougary21@paginegialle.it",
            "title": "Web Developer I"
        },
        {
            "id": 75,
            "name": "Jamil Burnham",
            "contact": "558 891 3656",
            "email": "jburnham22@nps.gov",
            "title": "Associate Professor"
        },
        {
            "id": 76,
            "name": "Cathrin Clemensen",
            "contact": "690 357 6538",
            "email": "cclemensen23@ucoz.com",
            "title": "Recruiting Manager"
        },
        {
            "id": 77,
            "name": "Adolf Matonin",
            "contact": "441 547 3811",
            "email": "amatonin24@chronoengine.com",
            "title": "Senior Editor"
        },
        {
            "id": 78,
            "name": "Dietrich Rumbold",
            "contact": "745 350 2310",
            "email": "drumbold25@patch.com",
            "title": "Electrical Engineer"
        },
        {
            "id": 79,
            "name": "Sib Jukes",
            "contact": "484 655 2263",
            "email": "sjukes26@utexas.edu",
            "title": "Nurse"
        },
        {
            "id": 80,
            "name": "Ichabod Pavolini",
            "contact": "483 765 9704",
            "email": "ipavolini27@goo.gl",
            "title": "Pharmacist"
        },
        {
            "id": 81,
            "name": "Holt Hursthouse",
            "contact": "225 834 6170",
            "email": "hhursthouse28@cnet.com",
            "title": "Structural Engineer"
        },
        {
            "id": 82,
            "name": "Colby Speariett",
            "contact": "528 345 7276",
            "email": "cspeariett29@java.com",
            "title": "Electrical Engineer"
        },
        {
            "id": 83,
            "name": "Trixi Gloucester",
            "contact": "541 251 9271",
            "email": "tgloucester2a@wired.com",
            "title": "Pharmacist"
        },
        {
            "id": 84,
            "name": "Godfrey Deerness",
            "contact": "152 451 4373",
            "email": "gdeerness2b@reference.com",
            "title": "Structural Analysis Engineer"
        },
        {
            "id": 85,
            "name": "Hobart Falla",
            "contact": "785 234 1380",
            "email": "hfalla2c@java.com",
            "title": "Business Systems Development Analyst"
        },
        {
            "id": 86,
            "name": "Windy Pridding",
            "contact": "562 805 8784",
            "email": "wpridding2d@tamu.edu",
            "title": "Software Consultant"
        },
        {
            "id": 87,
            "name": "Greta Enser",
            "contact": "456 887 4437",
            "email": "genser2e@github.io",
            "title": "Web Designer I"
        },
        {
            "id": 88,
            "name": "Binni Slocumb",
            "contact": "617 412 4391",
            "email": "bslocumb2f@phpbb.com",
            "title": "Web Designer I"
        },
        {
            "id": 89,
            "name": "Cherye Rizzardo",
            "contact": "532 933 9541",
            "email": "crizzardo2g@dagondesign.com",
            "title": "Quality Control Specialist"
        },
        {
            "id": 90,
            "name": "Janifer de Tocqueville",
            "contact": "963 815 2030",
            "email": "jde2h@github.io",
            "title": "Nurse"
        },
        {
            "id": 91,
            "name": "Thorn Henriksson",
            "contact": "659 532 5207",
            "email": "thenriksson2i@si.edu",
            "title": "Actuary"
        },
        {
            "id": 92,
            "name": "Kalina Ferreri",
            "contact": "804 542 7064",
            "email": "kferreri2j@networksolutions.com",
            "title": "Help Desk Technician"
        },
        {
            "id": 93,
            "name": "Athene O'Donoghue",
            "contact": "130 259 0584",
            "email": "aodonoghue2k@dropbox.com",
            "title": "Financial Analyst"
        },
        {
            "id": 94,
            "name": "Adaline Champkins",
            "contact": "201 245 8446",
            "email": "achampkins2l@1und1.de",
            "title": "Analog Circuit Design manager"
        },
        {
            "id": 95,
            "name": "Dara Baraja",
            "contact": "274 542 4457",
            "email": "dbaraja2m@livejournal.com",
            "title": "Geological Engineer"
        },
        {
            "id": 96,
            "name": "Scottie Mulberry",
            "contact": "880 227 0373",
            "email": "smulberry2n@canalblog.com",
            "title": "Legal Assistant"
        },
        {
            "id": 97,
            "name": "Harley Broadley",
            "contact": "577 261 2643",
            "email": "hbroadley2o@ca.gov",
            "title": "Editor"
        },
        {
            "id": 98,
            "name": "Joseph Gartan",
            "contact": "201 983 8078",
            "email": "jgartan2p@hugedomains.com",
            "title": "Accountant II"
        },
        {
            "id": 99,
            "name": "Eric Gelland",
            "contact": "164 264 7993",
            "email": "egelland2q@abc.net.au",
            "title": "Social Worker"
        },
        {
            "id": 100,
            "name": "Blythe Woodall",
            "contact": "212 362 8791",
            "email": "bwoodall2r@google.pl",
            "title": "Web Designer IV"
        },
        {
            "id": 101,
            "name": "Ash Oolahan",
            "contact": "887 615 0390",
            "email": "aoolahan2s@xing.com",
            "title": "Account Coordinator"
        },
        {
            "id": 102,
            "name": "Tabb Alesio",
            "contact": "769 365 0239",
            "email": "talesio2t@parallels.com",
            "title": "VP Marketing"
        },
        {
            "id": 103,
            "name": "Lizzie Flounders",
            "contact": "353 715 0803",
            "email": "lflounders2u@thetimes.co.uk",
            "title": "General Manager"
        },
        {
            "id": 104,
            "name": "Ricki Shortcliffe",
            "contact": "233 700 0830",
            "email": "rshortcliffe2v@jalbum.net",
            "title": "Community Outreach Specialist"
        },
        {
            "id": 105,
            "name": "Daloris Ganforthe",
            "contact": "532 589 4876",
            "email": "dganforthe2w@fc2.com",
            "title": "Tax Accountant"
        },
        {
            "id": 106,
            "name": "Allegra Bonsall",
            "contact": "474 823 2630",
            "email": "abonsall2x@seesaa.net",
            "title": "Nuclear Power Engineer"
        },
        {
            "id": 107,
            "name": "Gradeigh Yandell",
            "contact": "183 360 7407",
            "email": "gyandell2y@sfgate.com",
            "title": "Operator"
        },
        {
            "id": 108,
            "name": "Hayley Desmond",
            "contact": "132 628 3977",
            "email": "hdesmond2z@sogou.com",
            "title": "Operator"
        },
        {
            "id": 109,
            "name": "Dreddy Genn",
            "contact": "812 227 5586",
            "email": "dgenn30@yandex.ru",
            "title": "Clinical Specialist"
        },
        {
            "id": 110,
            "name": "Bronny MacConnal",
            "contact": "580 113 5430",
            "email": "bmacconnal31@microsoft.com",
            "title": "Product Engineer"
        },
        {
            "id": 111,
            "name": "Cordi Fenimore",
            "contact": "583 438 0140",
            "email": "cfenimore32@51.la",
            "title": "Graphic Designer"
        },
        {
            "id": 112,
            "name": "Carina Francesco",
            "contact": "589 202 9249",
            "email": "cfrancesco33@berkeley.edu",
            "title": "Design Engineer"
        },
        {
            "id": 113,
            "name": "Maxwell Robertazzi",
            "contact": "273 843 8360",
            "email": "mrobertazzi34@npr.org",
            "title": "Programmer Analyst II"
        },
        {
            "id": 114,
            "name": "Edin Darycott",
            "contact": "310 988 6324",
            "email": "edarycott35@sogou.com",
            "title": "Quality Engineer"
        },
        {
            "id": 115,
            "name": "Wiatt Olech",
            "contact": "306 805 5004",
            "email": "wolech36@baidu.com",
            "title": "Chemical Engineer"
        },
        {
            "id": 116,
            "name": "Isabella Rallinshaw",
            "contact": "747 244 1506",
            "email": "irallinshaw37@topsy.com",
            "title": "VP Sales"
        },
        {
            "id": 117,
            "name": "Mellisent Vanacci",
            "contact": "654 501 4643",
            "email": "mvanacci38@yolasite.com",
            "title": "Nurse Practicioner"
        },
        {
            "id": 118,
            "name": "Delores Custance",
            "contact": "604 821 6428",
            "email": "dcustance39@techcrunch.com",
            "title": "Accounting Assistant II"
        },
        {
            "id": 119,
            "name": "Quintina Murley",
            "contact": "866 728 8900",
            "email": "qmurley3a@aboutads.info",
            "title": "Web Developer III"
        },
        {
            "id": 120,
            "name": "Nicky Avrahm",
            "contact": "158 736 2077",
            "email": "navrahm3b@discuz.net",
            "title": "Senior Sales Associate"
        },
        {
            "id": 121,
            "name": "Annabelle Scurrer",
            "contact": "249 735 8471",
            "email": "ascurrer3c@wordpress.org",
            "title": "Structural Analysis Engineer"
        },
        {
            "id": 122,
            "name": "Whit Reston",
            "contact": "928 587 9610",
            "email": "wreston3d@wikipedia.org",
            "title": "Librarian"
        },
        {
            "id": 123,
            "name": "Arman Delacoste",
            "contact": "302 707 3056",
            "email": "adelacoste3e@sphinn.com",
            "title": "Help Desk Technician"
        },
        {
            "id": 124,
            "name": "Jilleen Heaton",
            "contact": "276 787 0720",
            "email": "jheaton3f@xrea.com",
            "title": "Help Desk Operator"
        },
        {
            "id": 125,
            "name": "Jacky Hebborne",
            "contact": "880 603 3483",
            "email": "jhebborne3g@hostgator.com",
            "title": "Systems Administrator III"
        },
        {
            "id": 126,
            "name": "Marlowe Klaffs",
            "contact": "335 679 5574",
            "email": "mklaffs3h@cpanel.net",
            "title": "Associate Professor"
        },
        {
            "id": 127,
            "name": "Wash Coulman",
            "contact": "569 433 5122",
            "email": "wcoulman3i@utexas.edu",
            "title": "Social Worker"
        },
        {
            "id": 128,
            "name": "Deborah Harlin",
            "contact": "909 271 7630",
            "email": "dharlin3j@thetimes.co.uk",
            "title": "Director of Sales"
        },
        {
            "id": 129,
            "name": "Putnam Gigg",
            "contact": "262 837 5620",
            "email": "pgigg3k@cbslocal.com",
            "title": "Chemical Engineer"
        },
        {
            "id": 130,
            "name": "Richmond Colter",
            "contact": "886 317 8824",
            "email": "rcolter3l@spiegel.de",
            "title": "Sales Associate"
        },
        {
            "id": 131,
            "name": "Therine Godley",
            "contact": "822 679 6475",
            "email": "tgodley3m@accuweather.com",
            "title": "Teacher"
        },
        {
            "id": 132,
            "name": "Meyer Pickring",
            "contact": "913 441 2911",
            "email": "mpickring3n@youtube.com",
            "title": "VP Product Management"
        },
        {
            "id": 133,
            "name": "Tamiko Ruf",
            "contact": "495 615 4329",
            "email": "truf3o@vinaora.com",
            "title": "Executive Secretary"
        },
        {
            "id": 134,
            "name": "Nil Straffon",
            "contact": "830 159 8525",
            "email": "nstraffon3p@yale.edu",
            "title": "Health Coach I"
        },
        {
            "id": 135,
            "name": "Niki Cockill",
            "contact": "822 153 0561",
            "email": "ncockill3q@rambler.ru",
            "title": "Research Associate"
        },
        {
            "id": 136,
            "name": "Wendall Dryburgh",
            "contact": "944 836 7268",
            "email": "wdryburgh3r@phpbb.com",
            "title": "VP Sales"
        },
        {
            "id": 137,
            "name": "Chrisse Skelhorne",
            "contact": "660 622 0824",
            "email": "cskelhorne3s@aol.com",
            "title": "Data Coordiator"
        },
        {
            "id": 138,
            "name": "Zenia Ingerman",
            "contact": "375 873 0235",
            "email": "zingerman3t@bluehost.com",
            "title": "Internal Auditor"
        },
        {
            "id": 139,
            "name": "Sydel MacCleod",
            "contact": "303 588 0176",
            "email": "smaccleod3u@livejournal.com",
            "title": "VP Product Management"
        },
        {
            "id": 140,
            "name": "Milka Gounard",
            "contact": "808 858 7158",
            "email": "mgounard3v@si.edu",
            "title": "Help Desk Technician"
        },
        {
            "id": 141,
            "name": "Griffin Maccraw",
            "contact": "453 474 9783",
            "email": "gmaccraw3w@plala.or.jp",
            "title": "Research Nurse"
        },
        {
            "id": 142,
            "name": "Dore Carneck",
            "contact": "718 304 7819",
            "email": "dcarneck3x@mysql.com",
            "title": "Engineer I"
        },
        {
            "id": 143,
            "name": "Reggie Veld",
            "contact": "375 762 5706",
            "email": "rveld3y@fda.gov",
            "title": "Nuclear Power Engineer"
        },
        {
            "id": 144,
            "name": "Melisandra Kane",
            "contact": "976 966 9035",
            "email": "mkane3z@weebly.com",
            "title": "Design Engineer"
        },
        {
            "id": 145,
            "name": "Nils McKinney",
            "contact": "988 709 8283",
            "email": "nmckinney40@storify.com",
            "title": "Physical Therapy Assistant"
        },
        {
            "id": 146,
            "name": "Ozzie Seage",
            "contact": "386 267 4743",
            "email": "oseage41@blogtalkradio.com",
            "title": "Recruiter"
        },
        {
            "id": 147,
            "name": "Gerik O' Mara",
            "contact": "857 734 3018",
            "email": "go42@51.la",
            "title": "Financial Analyst"
        },
        {
            "id": 148,
            "name": "Elijah Duffus",
            "contact": "100 120 2424",
            "email": "eduffus43@scribd.com",
            "title": "Civil Engineer"
        },
        {
            "id": 149,
            "name": "Gabie Delve",
            "contact": "742 597 6095",
            "email": "gdelve44@comsenz.com",
            "title": "VP Quality Control"
        },
        {
            "id": 150,
            "name": "Alain Mateuszczyk",
            "contact": "417 716 0915",
            "email": "amateuszczyk45@blinklist.com",
            "title": "Computer Systems Analyst II"
        },
        {
            "id": 151,
            "name": "Friedrich Grisewood",
            "contact": "869 565 2230",
            "email": "fgrisewood46@usatoday.com",
            "title": "Biostatistician II"
        },
        {
            "id": 152,
            "name": "Charmion Peasegod",
            "contact": "681 413 8025",
            "email": "cpeasegod47@si.edu",
            "title": "Junior Executive"
        },
        {
            "id": 153,
            "name": "Bell Starzaker",
            "contact": "768 901 2224",
            "email": "bstarzaker48@tamu.edu",
            "title": "Tax Accountant"
        },
        {
            "id": 154,
            "name": "Vassili Titchard",
            "contact": "410 809 2988",
            "email": "vtitchard49@naver.com",
            "title": "Junior Executive"
        },
        {
            "id": 155,
            "name": "Jonathon Aim",
            "contact": "935 970 9768",
            "email": "jaim4a@geocities.jp",
            "title": "Account Representative IV"
        },
        {
            "id": 156,
            "name": "Gabbey Mouton",
            "contact": "864 726 8178",
            "email": "gmouton4b@ifeng.com",
            "title": "Community Outreach Specialist"
        },
        {
            "id": 157,
            "name": "Adrien Cicco",
            "contact": "467 501 5634",
            "email": "acicco4c@edublogs.org",
            "title": "Environmental Specialist"
        },
        {
            "id": 158,
            "name": "Guinevere Wardlow",
            "contact": "167 310 1769",
            "email": "gwardlow4d@eventbrite.com",
            "title": "Librarian"
        },
        {
            "id": 159,
            "name": "Gabbi De Vaux",
            "contact": "369 579 4382",
            "email": "gde4e@indiegogo.com",
            "title": "Operator"
        },
        {
            "id": 160,
            "name": "Trevar Barrasse",
            "contact": "187 933 1583",
            "email": "tbarrasse4f@angelfire.com",
            "title": "Nurse"
        },
        {
            "id": 161,
            "name": "Korry Shawyers",
            "contact": "142 220 1067",
            "email": "kshawyers4g@hhs.gov",
            "title": "Associate Professor"
        },
        {
            "id": 162,
            "name": "Gherardo Siddell",
            "contact": "377 522 1790",
            "email": "gsiddell4h@g.co",
            "title": "Pharmacist"
        },
        {
            "id": 163,
            "name": "Klaus Hudel",
            "contact": "374 677 2176",
            "email": "khudel4i@free.fr",
            "title": "Dental Hygienist"
        },
        {
            "id": 164,
            "name": "Lee Daviot",
            "contact": "706 508 5812",
            "email": "ldaviot4j@state.tx.us",
            "title": "Environmental Tech"
        },
        {
            "id": 165,
            "name": "Lazaro Turfus",
            "contact": "892 499 7516",
            "email": "lturfus4k@php.net",
            "title": "Payment Adjustment Coordinator"
        },
        {
            "id": 166,
            "name": "Shepard Chappel",
            "contact": "284 108 2236",
            "email": "schappel4l@vinaora.com",
            "title": "Director of Sales"
        },
        {
            "id": 167,
            "name": "Sunny Weed",
            "contact": "358 677 8064",
            "email": "sweed4m@diigo.com",
            "title": "Software Test Engineer I"
        },
        {
            "id": 168,
            "name": "Thatcher Brea",
            "contact": "788 590 9839",
            "email": "tbrea4n@sakura.ne.jp",
            "title": "Pharmacist"
        },
        {
            "id": 169,
            "name": "Francisco Allmond",
            "contact": "324 584 3204",
            "email": "fallmond4o@weibo.com",
            "title": "Financial Analyst"
        },
        {
            "id": 170,
            "name": "Joelly MacGown",
            "contact": "154 993 1701",
            "email": "jmacgown4p@yahoo.com",
            "title": "Account Executive"
        },
        {
            "id": 171,
            "name": "Miquela Waggatt",
            "contact": "219 923 5194",
            "email": "mwaggatt4q@domainmarket.com",
            "title": "Quality Engineer"
        },
        {
            "id": 172,
            "name": "Irita Eivers",
            "contact": "485 300 7937",
            "email": "ieivers4r@narod.ru",
            "title": "Food Chemist"
        },
        {
            "id": 173,
            "name": "Michele Braisher",
            "contact": "943 847 2057",
            "email": "mbraisher4s@ucoz.ru",
            "title": "Database Administrator IV"
        },
        {
            "id": 174,
            "name": "Boycie Stiegar",
            "contact": "988 545 5886",
            "email": "bstiegar4t@dailymotion.com",
            "title": "Quality Engineer"
        },
        {
            "id": 175,
            "name": "Edna Bonds",
            "contact": "104 309 1044",
            "email": "ebonds4u@ehow.com",
            "title": "Account Executive"
        },
        {
            "id": 176,
            "name": "Cart Bidnall",
            "contact": "437 671 6269",
            "email": "cbidnall4v@vk.com",
            "title": "Dental Hygienist"
        },
        {
            "id": 177,
            "name": "Silvanus Reichartz",
            "contact": "303 349 9030",
            "email": "sreichartz4w@squarespace.com",
            "title": "Software Test Engineer III"
        },
        {
            "id": 178,
            "name": "Wilmette Seignior",
            "contact": "190 307 6018",
            "email": "wseignior4x@elegantthemes.com",
            "title": "Geological Engineer"
        },
        {
            "id": 179,
            "name": "Hobart Barford",
            "contact": "809 655 0400",
            "email": "hbarford4y@baidu.com",
            "title": "Research Assistant III"
        },
        {
            "id": 180,
            "name": "Cristobal Layson",
            "contact": "758 202 7054",
            "email": "clayson4z@qq.com",
            "title": "Junior Executive"
        },
        {
            "id": 181,
            "name": "Aurel Bethel",
            "contact": "652 476 0835",
            "email": "abethel50@blinklist.com",
            "title": "Help Desk Technician"
        },
        {
            "id": 182,
            "name": "Ray Durkin",
            "contact": "767 814 3026",
            "email": "rdurkin51@purevolume.com",
            "title": "Accountant II"
        },
        {
            "id": 183,
            "name": "Pascal Handscomb",
            "contact": "343 580 9254",
            "email": "phandscomb52@businesswire.com",
            "title": "Research Nurse"
        },
        {
            "id": 184,
            "name": "Constantine Cubitt",
            "contact": "332 659 1685",
            "email": "ccubitt53@wordpress.org",
            "title": "VP Quality Control"
        },
        {
            "id": 185,
            "name": "Amalita McPhillips",
            "contact": "902 598 5091",
            "email": "amcphillips54@noaa.gov",
            "title": "Business Systems Development Analyst"
        },
        {
            "id": 186,
            "name": "Aila Dunnan",
            "contact": "473 126 2257",
            "email": "adunnan55@spotify.com",
            "title": "Senior Editor"
        },
        {
            "id": 187,
            "name": "Abrahan McKibbin",
            "contact": "149 249 2925",
            "email": "amckibbin56@quantcast.com",
            "title": "Director of Sales"
        },
        {
            "id": 188,
            "name": "Corie Burfoot",
            "contact": "325 262 8638",
            "email": "cburfoot57@narod.ru",
            "title": "Administrative Assistant IV"
        },
        {
            "id": 189,
            "name": "Laurianne Windridge",
            "contact": "544 522 9819",
            "email": "lwindridge58@accuweather.com",
            "title": "Safety Technician I"
        },
        {
            "id": 190,
            "name": "Molly Mableson",
            "contact": "203 784 2814",
            "email": "mmableson59@webeden.co.uk",
            "title": "Nurse"
        },
        {
            "id": 191,
            "name": "Patrice Reedie",
            "contact": "480 696 0226",
            "email": "preedie5a@samsung.com",
            "title": "Community Outreach Specialist"
        },
        {
            "id": 192,
            "name": "Jason Sjostrom",
            "contact": "670 302 2684",
            "email": "jsjostrom5b@google.co.uk",
            "title": "VP Accounting"
        },
        {
            "id": 193,
            "name": "Marie-ann Pottinger",
            "contact": "403 608 7851",
            "email": "mpottinger5c@weebly.com",
            "title": "Marketing Manager"
        },
        {
            "id": 194,
            "name": "Dalis Hampton",
            "contact": "317 271 7845",
            "email": "dhampton5d@ucsd.edu",
            "title": "Accountant IV"
        },
        {
            "id": 195,
            "name": "Denny Makinson",
            "contact": "202 447 7312",
            "email": "dmakinson5e@bbb.org",
            "title": "Accounting Assistant II"
        },
        {
            "id": 196,
            "name": "Tracee Cowpland",
            "contact": "440 927 4943",
            "email": "tcowpland5f@exblog.jp",
            "title": "Analog Circuit Design manager"
        },
        {
            "id": 197,
            "name": "Doug Jeandot",
            "contact": "136 449 1826",
            "email": "djeandot5g@weibo.com",
            "title": "Payment Adjustment Coordinator"
        },
        {
            "id": 198,
            "name": "Karine Stickney",
            "contact": "868 232 2458",
            "email": "kstickney5h@tripod.com",
            "title": "Junior Executive"
        }
    ]
}